sqlalchemy_meta/__init__.py
sqlalchemy_meta/constant.py
sqlalchemy_meta/py.typed
sqlalchemy_meta/session.py
sqlalchemy_meta/typing.py
sqlalchemy_meta-0.4.0.dist-info/LICENSE.txt
sqlalchemy_meta-0.4.0.dist-info/WHEEL
sqlalchemy_meta-0.4.0.dist-info/METADATA
sqlalchemy_meta-0.4.0.dist-info/RECORD
